README.md
setup.py
myslim.egg-info/PKG-INFO
myslim.egg-info/SOURCES.txt
myslim.egg-info/dependency_links.txt
myslim.egg-info/requires.txt
myslim.egg-info/top_level.txt
slim/__init__.py
slim/app.py
slim/error.py
slim/log.py