Metadata-Version: 1.0
Name: myslim
Version: 0.1
Summary: A slim web framework
Home-page: https://github.com/MMengyaoXu/slim
Author: mengyao.xu
Author-email: 3277018467@qq.com
License: UNKNOWN
Platform: UNKNOWN
